benchmark/__init__.py
benchmark/functions.py
benchmark/plotting.py
examples/__init__.py
examples/cma_es_example.py
examples/differential_evolution_example.py
examples/harmony_search_example.py
examples/simulated_annealing_example.py
examples/sincos_example.py
examples/tabu_search_example.py
examples/variable_depth_search_example.py
keras_tuner_extensionpack/__init__.py
keras_tuner_extensionpack/cma_es_algorithm.py
keras_tuner_extensionpack/differential_evolution.py
keras_tuner_extensionpack/harmony_search.py
keras_tuner_extensionpack/simulated_annealing_search.py
keras_tuner_extensionpack/sin_cosine_algorithm.py
keras_tuner_extensionpack/tabu_search.py
keras_tuner_extensionpack/test_new_optimizers.py
keras_tuner_extensionpack/tools/__init__.py
keras_tuner_extensionpack/tools/converters.py
keras_tuner_extensionpack/tools/exception_checks.py
keras_tuner_extensionpack/tools/type_definitions.py
keras_tuner_extensionpack/variable_depth_search.py
keras_tuner_extensionpack-0.1.0.dist-info/LICENSE.md
keras_tuner_extensionpack-0.1.0.dist-info/METADATA
keras_tuner_extensionpack-0.1.0.dist-info/WHEEL
keras_tuner_extensionpack-0.1.0.dist-info/RECORD
