Metadata-Version: 2.1
Name: keras-tuner-extensionpack
Version: 0.1.0
Summary: An extension pack for keras-tuner for providing additional optimizers.
Home-page: https://github.com/Anselmoo/keras-tuner-extensionpack
License: Apache-2.0
Keywords: keras-tuner,optimizers,keras,tensorflow
Author: Anselm Hahn
Author-email: Anselm.Hahn@gmail.com
Maintainer: Anselm Hahn
Maintainer-email: Anselm.Hahn@gmail.com
Requires-Python: >=3.8,<3.12
Classifier: Development Status :: 3 - Alpha
Classifier: Intended Audience :: Developers
Classifier: Intended Audience :: Science/Research
Classifier: License :: OSI Approved :: Apache Software License
Classifier: Programming Language :: Python :: 3
Classifier: Programming Language :: Python :: 3.8
Classifier: Programming Language :: Python :: 3.9
Classifier: Programming Language :: Python :: 3.10
Classifier: Programming Language :: Python :: 3.11
Classifier: Programming Language :: Python :: 3.12
Classifier: Topic :: Scientific/Engineering :: Artificial Intelligence
Classifier: Topic :: Software Development :: Libraries
Classifier: Topic :: Software Development :: Libraries :: Python Modules
Provides-Extra: all
Provides-Extra: scipy
Provides-Extra: tensorflow
Requires-Dist: keras-tuner (>=1.4.6,<2.0.0)
Requires-Dist: numpy (<1.26.4) ; python_version < "3.9"
Requires-Dist: numpy (>=1.26.4,<2.0.0) ; python_version >= "3.9" and python_version < "4.0"
Requires-Dist: scipy (<1.12.0) ; (python_version < "3.9") and (extra == "scipy" or extra == "all")
Requires-Dist: scipy (>=1.12.0,<2.0.0) ; (python_version >= "3.9" and python_version < "4.0") and (extra == "scipy" or extra == "all")
Requires-Dist: tensorflow (<2.15.0.post1) ; (python_version < "3.9") and (extra == "tensorflow" or extra == "all")
Requires-Dist: tensorflow (<3.0.0) ; (python_version >= "3.9" and python_version < "4.0") and (extra == "tensorflow" or extra == "all")
Requires-Dist: update (>=0.0.1,<0.0.2)
Project-URL: Repository, https://github.com/Anselmoo/keras-tuner-extensionpack
